telescope/__init__.py
telescope/cli.py
telescope/client.py
telescope/context.py
telescope/decorators.py
telescope/integrations.py
telescope_python-1.0.5.dist-info/METADATA
telescope_python-1.0.5.dist-info/WHEEL
telescope_python-1.0.5.dist-info/entry_points.txt
telescope_python-1.0.5.dist-info/RECORD
