Metadata-Version: 2.1
Name: telescope-python
Version: 1.0.5
Summary: Python client for Telescope error monitoring
Home-page: https://github.com/us-telescope/telescope-python
License: MIT
Keywords: telescope,error-monitoring,observability,opentelemetry,logging
Author: Telescope Team
Author-email: hello@ultron.studio
Requires-Python: >=3.8,<4.0
Classifier: Development Status :: 4 - Beta
Classifier: Intended Audience :: Developers
Classifier: License :: OSI Approved :: MIT License
Classifier: Operating System :: OS Independent
Classifier: Programming Language :: Python :: 3
Classifier: Programming Language :: Python :: 3.8
Classifier: Programming Language :: Python :: 3.9
Classifier: Programming Language :: Python :: 3.10
Classifier: Programming Language :: Python :: 3.11
Classifier: Programming Language :: Python :: 3.12
Classifier: Programming Language :: Python :: 3.13
Classifier: Topic :: Software Development :: Libraries :: Python Modules
Classifier: Topic :: System :: Logging
Classifier: Topic :: System :: Monitoring
Provides-Extra: all
Provides-Extra: celery
Provides-Extra: django
Provides-Extra: fastapi
Provides-Extra: flask
Requires-Dist: opentelemetry-api (>=1.20.0,<2.0.0)
Requires-Dist: opentelemetry-exporter-otlp (>=1.20.0,<2.0.0)
Requires-Dist: opentelemetry-instrumentation-celery (>=0.41b0,<0.42) ; extra == "celery" or extra == "all"
Requires-Dist: opentelemetry-instrumentation-django (>=0.41b0,<0.42) ; extra == "django" or extra == "all"
Requires-Dist: opentelemetry-instrumentation-fastapi (>=0.41b0,<0.42) ; extra == "fastapi" or extra == "all"
Requires-Dist: opentelemetry-instrumentation-flask (>=0.41b0,<0.42) ; extra == "flask" or extra == "all"
Requires-Dist: opentelemetry-instrumentation-logging (>=0.41b0,<0.42)
Requires-Dist: opentelemetry-instrumentation-psycopg2 (>=0.41b0,<0.42) ; extra == "django" or extra == "all"
Requires-Dist: opentelemetry-instrumentation-requests (>=0.41b0,<0.42)
Requires-Dist: opentelemetry-instrumentation-sqlalchemy (>=0.41b0,<0.42) ; extra == "flask" or extra == "fastapi" or extra == "all"
Requires-Dist: opentelemetry-sdk (>=1.20.0,<2.0.0)
Requires-Dist: requests (>=2.25.0,<3.0.0)
Project-URL: Documentation, https://github.com/us-telescope/telescope-python#readme
Project-URL: Repository, https://github.com/us-telescope/telescope-python
